chironpy/__init__.py
chironpy/constants.py
chironpy/examples/data/18360138543_ACTIVITY_Osaka_Marathon_2025.fit
chironpy/examples/data/2020-06-01-16-52-40.fit
chironpy/examples/data/3173437224.tcx
chironpy/examples/data/4078723797.fit
chironpy/examples/data/4078723797_strava.gpx
chironpy/examples/data/4801048867.fit
chironpy/examples/data/4801048867_strava.gpx
chironpy/examples/data/6449921903_ACTIVITY.fit
chironpy/examples/data/6471559601_ACTIVITY.fit
chironpy/examples/data/74d893f7-1349-4b2c-ac5f-60246396b8b1_local_strava_Osaka_Marathon_2025.json
chironpy/examples/data/8eb40499-450a-436e-adac-c3ba95bf1834_local_strava.json
chironpy/examples/data/activity_4078723797.gpx
chironpy/examples/data/activity_4078723797.tcx
chironpy/examples/data/activity_4801048867.gpx
chironpy/examples/data/activity_4801048867.tcx
chironpy/examples/data/activity_5039744860.gpx
chironpy/examples/data/activity_5039744860.tcx
chironpy/examples/index.yml
chironpy/examples/utils.py
chironpy/hrm/__init__.py
chironpy/hrm/heartrate_models.py
chironpy/io/__init__.py
chironpy/io/exceptions.py
chironpy/io/fit.py
chironpy/io/fit_profile.json
chironpy/io/generic.py
chironpy/io/gpx.py
chironpy/io/local_strava.py
chironpy/io/models.py
chironpy/io/strava.py
chironpy/io/tcx.py
chironpy/io/utils.py
chironpy/metrics/__init__.py
chironpy/metrics/core.py
chironpy/metrics/heartrate.py
chironpy/metrics/location.py
chironpy/metrics/power.py
chironpy/metrics/speed.py
chironpy/metrics/vert.py
chironpy/models/__init__.py
chironpy/models/workout.py
chironpy/pandas.py
chironpy/pdm/__init__.py
chironpy/pdm/regressors.py
chironpy/pdm/w_prime_balance.py
chironpy/utils.py
chironpy-0.28.1.dist-info/LICENSE
chironpy-0.28.1.dist-info/METADATA
chironpy-0.28.1.dist-info/WHEEL
chironpy-0.28.1.dist-info/RECORD
