Metadata-Version: 2.3
Name: chironpy
Version: 0.28.1
Summary: Workout analysis
License: MIT
Author: Clive Gross
Author-email: clive@chironapp.com
Requires-Python: >=3.10,<4.0.0
Classifier: License :: OSI Approved :: MIT License
Classifier: Programming Language :: Python :: 3
Classifier: Programming Language :: Python :: 3.10
Classifier: Programming Language :: Python :: 3.11
Classifier: Programming Language :: Python :: 3.12
Classifier: Programming Language :: Python :: 3.13
Requires-Dist: fitparse (>=1.1.0,<2.0.0)
Requires-Dist: lmfit (>=1.0.0,<2.0.0)
Requires-Dist: matplotlib (>=3.3.4,<4.0.0)
Requires-Dist: mkdocs-material[icons] (>=9.6.12,<10.0.0)
Requires-Dist: numpy (>=1.21,<1.24)
Requires-Dist: pandas (>=1.5.2,<2.0.0)
Requires-Dist: pydantic (>=2.0,<3.0)
Requires-Dist: pyyaml (>=6.0.0,<7.0.0)
Requires-Dist: requests (>=2.23.0,<3.0.0)
Requires-Dist: scikit-learn (>=0.23.1)
Requires-Dist: scipy (>=1.4.1,<2.0.0)
Requires-Dist: stravalib (>=2.0.0,<3.0.0)
Project-URL: Documentation, https://chironapp.github.io/chironpy/
Project-URL: Homepage, https://chironapp.github.io/chironpy/
Project-URL: Repository, https://github.com/chironapp/chironpy
